setup.py
udacity_distributions_sahikabetul/Binomialdistribution.py
udacity_distributions_sahikabetul/Gaussiandistribution.py
udacity_distributions_sahikabetul/Generaldistribution.py
udacity_distributions_sahikabetul/__init__.py
udacity_distributions_sahikabetul.egg-info/PKG-INFO
udacity_distributions_sahikabetul.egg-info/SOURCES.txt
udacity_distributions_sahikabetul.egg-info/dependency_links.txt
udacity_distributions_sahikabetul.egg-info/not-zip-safe
udacity_distributions_sahikabetul.egg-info/top_level.txt