Metadata-Version: 1.0
Name: udacity-distributions-sahikabetul
Version: 0.1
Summary: Gaussian and Binomial distributions
Home-page: UNKNOWN
Author: Sahika Betul
Author-email: sahika.betul@gmail.com
License: UNKNOWN
Platform: UNKNOWN
